README.txt
setup.py
newticketlikethis/__init__.py
newticketlikethis/core.py
newticketlikethis/interfaces.py
newticketlikethis/policies.py
trac_NewTicketLikeThisPlugin.egg-info/PKG-INFO
trac_NewTicketLikeThisPlugin.egg-info/SOURCES.txt
trac_NewTicketLikeThisPlugin.egg-info/dependency_links.txt
trac_NewTicketLikeThisPlugin.egg-info/entry_points.txt
trac_NewTicketLikeThisPlugin.egg-info/not-zip-safe
trac_NewTicketLikeThisPlugin.egg-info/top_level.txt