Metadata-Version: 1.0
Name: trac-NewTicketLikeThisPlugin
Version: 0.1
Summary: Pluggable framework for 'cloning' Trac tickets according to custom business logic
Home-page: http://trac-hacks.org/wiki/NewTicketLikeThisPlugin
Author: Ethan Jucovy
Author-email: ejucovy@gmail.com
License: BSD
Keywords: trac plugin
Platform: UNKNOWN
